{
  "configVersion": 1,
  "timestamp": 1571067342170,
  "index": "https://gPierre56.github.io/conference-ionic/index.html",
  "assetGroups": [
    {
      "name": "app",
      "installMode": "prefetch",
      "updateMode": "prefetch",
      "urls": [
        "https://gPierre56.github.io/conference-ionic/1-es2015.506ff25b20e865f460e8.js",
        "https://gPierre56.github.io/conference-ionic/1-es5.6930c827ef6729028c1a.js",
        "https://gPierre56.github.io/conference-ionic/10-es2015.455ef8359f6dc028c348.js",
        "https://gPierre56.github.io/conference-ionic/10-es5.3392a83fc6dbe5a1cb6c.js",
        "https://gPierre56.github.io/conference-ionic/100-es2015.aaf51250e6baa3942580.js",
        "https://gPierre56.github.io/conference-ionic/100-es5.1b2321d18c397cddd5ae.js",
        "https://gPierre56.github.io/conference-ionic/101-es2015.33f5aaeada3454e9d41c.js",
        "https://gPierre56.github.io/conference-ionic/101-es5.5497f59ee3ed1801ee9c.js",
        "https://gPierre56.github.io/conference-ionic/102-es2015.cbab1aa44c65cde1cac0.js",
        "https://gPierre56.github.io/conference-ionic/102-es5.ab859ea2111b221607a9.js",
        "https://gPierre56.github.io/conference-ionic/103-es2015.910841bdf151d3e82aa8.js",
        "https://gPierre56.github.io/conference-ionic/103-es5.85fc077886fb7201e97b.js",
        "https://gPierre56.github.io/conference-ionic/104-es2015.2149f1ba94fb3bb985cb.js",
        "https://gPierre56.github.io/conference-ionic/104-es5.0f8430d63d716829761b.js",
        "https://gPierre56.github.io/conference-ionic/105-es2015.3aa7b622d24f39954d3c.js",
        "https://gPierre56.github.io/conference-ionic/105-es5.6dc9170fa5eedff740b6.js",
        "https://gPierre56.github.io/conference-ionic/106-es2015.84bedd65d4c90aac0e48.js",
        "https://gPierre56.github.io/conference-ionic/106-es5.8a9e5da74fd7de53ff56.js",
        "https://gPierre56.github.io/conference-ionic/107-es2015.67f6da47f7cb183a9d5e.js",
        "https://gPierre56.github.io/conference-ionic/107-es5.5b23804aac2b17b0c89e.js",
        "https://gPierre56.github.io/conference-ionic/108-es2015.3b8a75f77830a8b67a55.js",
        "https://gPierre56.github.io/conference-ionic/11-es2015.97e44b7d061609ac3248.js",
        "https://gPierre56.github.io/conference-ionic/11-es5.f6f476ba7e4e398b0476.js",
        "https://gPierre56.github.io/conference-ionic/14-es5.b915df1d3775570a79b5.js",
        "https://gPierre56.github.io/conference-ionic/15-es2015.a48e7a64a16d8d73f0ab.js",
        "https://gPierre56.github.io/conference-ionic/15-es5.b25ce20251ca6ab5a772.js",
        "https://gPierre56.github.io/conference-ionic/16-es2015.85e3cae62ec7dd4cbc77.js",
        "https://gPierre56.github.io/conference-ionic/16-es5.b527e30b716540129a00.js",
        "https://gPierre56.github.io/conference-ionic/17-es2015.c0a615fc11a491cf42b7.js",
        "https://gPierre56.github.io/conference-ionic/17-es5.255eee7b5c1fe0ab299b.js",
        "https://gPierre56.github.io/conference-ionic/18-es2015.7e0de0af7fc56bbce2ce.js",
        "https://gPierre56.github.io/conference-ionic/18-es5.d98d198729100506a5df.js",
        "https://gPierre56.github.io/conference-ionic/19-es2015.9bc0dfb9ed71d85da520.js",
        "https://gPierre56.github.io/conference-ionic/19-es5.f760cb2a84b20258791d.js",
        "https://gPierre56.github.io/conference-ionic/2-es5.6f6b2d6e12a843531dd6.js",
        "https://gPierre56.github.io/conference-ionic/20-es2015.dfe600a78fe380c1686b.js",
        "https://gPierre56.github.io/conference-ionic/20-es5.8d3f6669648ea4b900c5.js",
        "https://gPierre56.github.io/conference-ionic/21-es2015.dccd515fe19983dd1bd9.js",
        "https://gPierre56.github.io/conference-ionic/21-es5.1e5284b2a22f6ebff3c7.js",
        "https://gPierre56.github.io/conference-ionic/22-es2015.b0736d043c78a0d66f46.js",
        "https://gPierre56.github.io/conference-ionic/22-es5.ebf07d37eb5c607c2d4f.js",
        "https://gPierre56.github.io/conference-ionic/23-es2015.32e06cbaa8d6e427fdc7.js",
        "https://gPierre56.github.io/conference-ionic/23-es5.b3e8e472d9070605a48c.js",
        "https://gPierre56.github.io/conference-ionic/24-es2015.2fc0339b566cc91ddf0d.js",
        "https://gPierre56.github.io/conference-ionic/24-es5.1dc15dbb0f0c8dab69be.js",
        "https://gPierre56.github.io/conference-ionic/25-es2015.e39eb0d5961ee4214800.js",
        "https://gPierre56.github.io/conference-ionic/25-es5.abec9e00e60a27ea15fa.js",
        "https://gPierre56.github.io/conference-ionic/26-es2015.4f5042b04262fc141030.js",
        "https://gPierre56.github.io/conference-ionic/26-es5.12f3ec8290d310c56590.js",
        "https://gPierre56.github.io/conference-ionic/27-es2015.3096d4e5b8f222489a80.js",
        "https://gPierre56.github.io/conference-ionic/27-es5.2c64b9e233c503f6d9a2.js",
        "https://gPierre56.github.io/conference-ionic/28-es2015.5641e573373a63d7e104.js",
        "https://gPierre56.github.io/conference-ionic/28-es5.b3cd899787837c08a715.js",
        "https://gPierre56.github.io/conference-ionic/29-es2015.ea3d302ad4c58081baec.js",
        "https://gPierre56.github.io/conference-ionic/29-es5.e1b8fe1123ed93716db5.js",
        "https://gPierre56.github.io/conference-ionic/3-es2015.d6ac8d704fa8c21d31e7.js",
        "https://gPierre56.github.io/conference-ionic/30-es2015.d31d5897b87fceb212b3.js",
        "https://gPierre56.github.io/conference-ionic/30-es5.561b08026c587a74d39e.js",
        "https://gPierre56.github.io/conference-ionic/31-es2015.f15ac1eceb9da0315c5d.js",
        "https://gPierre56.github.io/conference-ionic/31-es5.c283b8521f673444cab0.js",
        "https://gPierre56.github.io/conference-ionic/32-es2015.34b25343c16e47ccec94.js",
        "https://gPierre56.github.io/conference-ionic/32-es5.eaa40abede764cf1166e.js",
        "https://gPierre56.github.io/conference-ionic/33-es2015.f95f44e6ac331288aa43.js",
        "https://gPierre56.github.io/conference-ionic/33-es5.55245bd8a37a3fa95b45.js",
        "https://gPierre56.github.io/conference-ionic/34-es2015.645d89d2c43f107274fd.js",
        "https://gPierre56.github.io/conference-ionic/34-es5.59dd8835b5003255b3e6.js",
        "https://gPierre56.github.io/conference-ionic/35-es2015.260c0991913dde1c4b41.js",
        "https://gPierre56.github.io/conference-ionic/35-es5.69118e65501ab528c274.js",
        "https://gPierre56.github.io/conference-ionic/36-es2015.3c8798b13b4059f656c9.js",
        "https://gPierre56.github.io/conference-ionic/36-es5.6b82c1657c44f3940ca0.js",
        "https://gPierre56.github.io/conference-ionic/37-es2015.1392128ef0f8c2bce11d.js",
        "https://gPierre56.github.io/conference-ionic/37-es5.3ff11b07b7f9a103c293.js",
        "https://gPierre56.github.io/conference-ionic/38-es2015.00d37447fe2e0fe53155.js",
        "https://gPierre56.github.io/conference-ionic/38-es5.79997d83d7d8f79ff4ea.js",
        "https://gPierre56.github.io/conference-ionic/39-es2015.e7a29d89e6eb40eda240.js",
        "https://gPierre56.github.io/conference-ionic/39-es5.cdc4d4564284188f4402.js",
        "https://gPierre56.github.io/conference-ionic/4-es2015.371c8f0a5554410fe343.js",
        "https://gPierre56.github.io/conference-ionic/4-es5.edabf8227e7fef5c841c.js",
        "https://gPierre56.github.io/conference-ionic/40-es2015.15e987d96911d8c1cf94.js",
        "https://gPierre56.github.io/conference-ionic/40-es5.d668b0f5d1d6ec7d02a4.js",
        "https://gPierre56.github.io/conference-ionic/41-es2015.772424b3620d34853f41.js",
        "https://gPierre56.github.io/conference-ionic/41-es5.9217e193184c49fe4eda.js",
        "https://gPierre56.github.io/conference-ionic/42-es2015.e137dbbb78837b3e05a1.js",
        "https://gPierre56.github.io/conference-ionic/42-es5.6299ce27a36e2f45b1db.js",
        "https://gPierre56.github.io/conference-ionic/43-es2015.6298e4dab0981848673e.js",
        "https://gPierre56.github.io/conference-ionic/43-es5.c6841a141d717509bed0.js",
        "https://gPierre56.github.io/conference-ionic/44-es2015.c7dbd2b671620f98113a.js",
        "https://gPierre56.github.io/conference-ionic/44-es5.048dff59bed0fcf8a167.js",
        "https://gPierre56.github.io/conference-ionic/45-es2015.66ffd27c58acdd84ade6.js",
        "https://gPierre56.github.io/conference-ionic/45-es5.7ded4915d9d9405a3696.js",
        "https://gPierre56.github.io/conference-ionic/46-es2015.1641f73d2a8a3380366e.js",
        "https://gPierre56.github.io/conference-ionic/46-es5.22724aaa4ee2c0e513bb.js",
        "https://gPierre56.github.io/conference-ionic/47-es2015.db5ef8d3e342b9b27ff0.js",
        "https://gPierre56.github.io/conference-ionic/47-es5.917398f6c026b709a7d9.js",
        "https://gPierre56.github.io/conference-ionic/48-es2015.950a861e96b11425e199.js",
        "https://gPierre56.github.io/conference-ionic/48-es5.7bbd43864e352a9a34cc.js",
        "https://gPierre56.github.io/conference-ionic/49-es2015.14f7060d83207c319a27.js",
        "https://gPierre56.github.io/conference-ionic/49-es5.ee3c28c41931140f7f98.js",
        "https://gPierre56.github.io/conference-ionic/5-es2015.86cf410eedc475bc352d.js",
        "https://gPierre56.github.io/conference-ionic/5-es5.6102aae1e25434463526.js",
        "https://gPierre56.github.io/conference-ionic/50-es2015.cfa9c782f46594af2afc.js",
        "https://gPierre56.github.io/conference-ionic/50-es5.ef26b16a0d45f52b5b91.js",
        "https://gPierre56.github.io/conference-ionic/51-es2015.7c4054d82b9d309962cc.js",
        "https://gPierre56.github.io/conference-ionic/51-es5.b2b3f52ff58de9410ea1.js",
        "https://gPierre56.github.io/conference-ionic/52-es2015.68a8aae41cc7c817b672.js",
        "https://gPierre56.github.io/conference-ionic/52-es5.417abfbe7aaa42ede37b.js",
        "https://gPierre56.github.io/conference-ionic/53-es2015.a6d5de20e7a55b381656.js",
        "https://gPierre56.github.io/conference-ionic/53-es5.3e73abe68375da46dcb6.js",
        "https://gPierre56.github.io/conference-ionic/54-es2015.93655bb7d36902e6beae.js",
        "https://gPierre56.github.io/conference-ionic/54-es5.73477fe316a56c004d0e.js",
        "https://gPierre56.github.io/conference-ionic/55-es2015.951877a27feab8a3fb4d.js",
        "https://gPierre56.github.io/conference-ionic/55-es5.4b166133326eef8ce942.js",
        "https://gPierre56.github.io/conference-ionic/56-es2015.048de950cbd88c193ff9.js",
        "https://gPierre56.github.io/conference-ionic/56-es5.4847a7cbaaeb3592a353.js",
        "https://gPierre56.github.io/conference-ionic/57-es2015.e11902d0fd03853c7a1d.js",
        "https://gPierre56.github.io/conference-ionic/57-es5.0bc7f30eb476df0aa0bc.js",
        "https://gPierre56.github.io/conference-ionic/58-es2015.b406f7bc5ae1436da0b1.js",
        "https://gPierre56.github.io/conference-ionic/58-es5.0be5ddc2aa773f33f08c.js",
        "https://gPierre56.github.io/conference-ionic/59-es2015.b51890c42ba9a1e96727.js",
        "https://gPierre56.github.io/conference-ionic/59-es5.9cdffe95c18e41fe446d.js",
        "https://gPierre56.github.io/conference-ionic/6-es2015.4993ef75f626ddf24fe7.js",
        "https://gPierre56.github.io/conference-ionic/6-es5.376fc0f1fcc0c5e8bac8.js",
        "https://gPierre56.github.io/conference-ionic/60-es2015.2825494580af64205f7f.js",
        "https://gPierre56.github.io/conference-ionic/60-es5.e256bbfe13c4861b4220.js",
        "https://gPierre56.github.io/conference-ionic/61-es2015.1604474cf28536fc2b95.js",
        "https://gPierre56.github.io/conference-ionic/61-es5.bae29f59dab18fb16549.js",
        "https://gPierre56.github.io/conference-ionic/62-es2015.30ec7cb05ab02ea0eddd.js",
        "https://gPierre56.github.io/conference-ionic/62-es5.857fd05cf62531bd7f76.js",
        "https://gPierre56.github.io/conference-ionic/63-es2015.594228baeaf7c619f242.js",
        "https://gPierre56.github.io/conference-ionic/63-es5.87fbb8fb55731612ff29.js",
        "https://gPierre56.github.io/conference-ionic/64-es2015.8ae119398f7f12b8c784.js",
        "https://gPierre56.github.io/conference-ionic/64-es5.19182598fed99a197593.js",
        "https://gPierre56.github.io/conference-ionic/65-es2015.10f7e4a3d15739f4b934.js",
        "https://gPierre56.github.io/conference-ionic/65-es5.63b2b7250ebead0b015b.js",
        "https://gPierre56.github.io/conference-ionic/66-es2015.c53b72ad48a60cfe9f32.js",
        "https://gPierre56.github.io/conference-ionic/66-es5.08b288969ab7d2331904.js",
        "https://gPierre56.github.io/conference-ionic/67-es2015.99fe52f2e79ffdd1dcbd.js",
        "https://gPierre56.github.io/conference-ionic/67-es5.bf861e22959300768938.js",
        "https://gPierre56.github.io/conference-ionic/68-es2015.744f7eb16ebc0ed2a97e.js",
        "https://gPierre56.github.io/conference-ionic/68-es5.31bd41f78c5d45822e6d.js",
        "https://gPierre56.github.io/conference-ionic/69-es2015.7578175b187a4f2c0eca.js",
        "https://gPierre56.github.io/conference-ionic/69-es5.c3e199b940322f180e0f.js",
        "https://gPierre56.github.io/conference-ionic/7-es2015.b444c9948e95b49214bf.js",
        "https://gPierre56.github.io/conference-ionic/7-es5.0e9f9439eaf8c9ddf366.js",
        "https://gPierre56.github.io/conference-ionic/70-es2015.690c1df7fb385e6cd1bd.js",
        "https://gPierre56.github.io/conference-ionic/70-es5.99bccd79a0cdc27dc567.js",
        "https://gPierre56.github.io/conference-ionic/71-es2015.4741b251e9e13645fb02.js",
        "https://gPierre56.github.io/conference-ionic/71-es5.9fbad1a0115097f7d905.js",
        "https://gPierre56.github.io/conference-ionic/72-es2015.d91b2777af3836f84acc.js",
        "https://gPierre56.github.io/conference-ionic/72-es5.572c39ea88b2c131a981.js",
        "https://gPierre56.github.io/conference-ionic/73-es2015.f3e6da05c211ee94bcd2.js",
        "https://gPierre56.github.io/conference-ionic/73-es5.50e3a69dc9d5c0a8c3e1.js",
        "https://gPierre56.github.io/conference-ionic/74-es2015.d607ec0ea03027f94da9.js",
        "https://gPierre56.github.io/conference-ionic/74-es5.7f646a21628a384553f7.js",
        "https://gPierre56.github.io/conference-ionic/75-es2015.f3cd6953b483750c0701.js",
        "https://gPierre56.github.io/conference-ionic/75-es5.26ff06fedb95681e5ab3.js",
        "https://gPierre56.github.io/conference-ionic/76-es2015.dc1bb06bcf0ab80f26fe.js",
        "https://gPierre56.github.io/conference-ionic/76-es5.a99eb5fce07ac1d9a855.js",
        "https://gPierre56.github.io/conference-ionic/77-es2015.9e99489ca921e8d183b4.js",
        "https://gPierre56.github.io/conference-ionic/77-es5.8210b01549fac032d908.js",
        "https://gPierre56.github.io/conference-ionic/78-es2015.506df84b45c56d27814e.js",
        "https://gPierre56.github.io/conference-ionic/78-es5.3eea6b4fb9863a46da85.js",
        "https://gPierre56.github.io/conference-ionic/79-es2015.5d7ab4a7066d74b95014.js",
        "https://gPierre56.github.io/conference-ionic/79-es5.d634204efcea24eeb90c.js",
        "https://gPierre56.github.io/conference-ionic/8-es2015.c1fa4b5905a5429a6aa8.js",
        "https://gPierre56.github.io/conference-ionic/8-es5.c443222dbdfb1d668d2d.js",
        "https://gPierre56.github.io/conference-ionic/80-es2015.fbcfa2255d588aa14293.js",
        "https://gPierre56.github.io/conference-ionic/80-es5.03dcc11f84995640d6bf.js",
        "https://gPierre56.github.io/conference-ionic/81-es2015.dda141d7a3dd6222409c.js",
        "https://gPierre56.github.io/conference-ionic/81-es5.d0c189d84c760b74a80d.js",
        "https://gPierre56.github.io/conference-ionic/82-es2015.60b9e137c00308184784.js",
        "https://gPierre56.github.io/conference-ionic/82-es5.20317392ff5496a266fc.js",
        "https://gPierre56.github.io/conference-ionic/83-es2015.8a2a0332334790c287d7.js",
        "https://gPierre56.github.io/conference-ionic/83-es5.dcca598ca67a95acd6d7.js",
        "https://gPierre56.github.io/conference-ionic/84-es2015.442f9e5c3e8f736e718b.js",
        "https://gPierre56.github.io/conference-ionic/84-es5.619b30d5f504326e23c4.js",
        "https://gPierre56.github.io/conference-ionic/85-es2015.779a16fab2997558968b.js",
        "https://gPierre56.github.io/conference-ionic/85-es5.2641a7f2f9b23e2b9daf.js",
        "https://gPierre56.github.io/conference-ionic/86-es2015.afec048412c0677beeb4.js",
        "https://gPierre56.github.io/conference-ionic/86-es5.8963782ad70b13ea76a9.js",
        "https://gPierre56.github.io/conference-ionic/87-es2015.1604898ef93b623d15d8.js",
        "https://gPierre56.github.io/conference-ionic/87-es5.2f09513c8a15168324e8.js",
        "https://gPierre56.github.io/conference-ionic/88-es2015.b809d6b8e8cf95f110d9.js",
        "https://gPierre56.github.io/conference-ionic/88-es5.2d92dfd4298205600aa7.js",
        "https://gPierre56.github.io/conference-ionic/89-es2015.956be521b707756d3fd1.js",
        "https://gPierre56.github.io/conference-ionic/89-es5.197ccab10bb4d345e43d.js",
        "https://gPierre56.github.io/conference-ionic/9-es2015.291f8c220aba2f0e0034.js",
        "https://gPierre56.github.io/conference-ionic/9-es5.937a5dc11fc15fb92a3c.js",
        "https://gPierre56.github.io/conference-ionic/90-es2015.c477740d144aea238433.js",
        "https://gPierre56.github.io/conference-ionic/90-es5.6bc191813da03929ac5e.js",
        "https://gPierre56.github.io/conference-ionic/91-es2015.7b30a8097f1f36565c18.js",
        "https://gPierre56.github.io/conference-ionic/91-es5.b2c4cb933948b7c1dfc9.js",
        "https://gPierre56.github.io/conference-ionic/92-es2015.6e3def503fa6b508d7bd.js",
        "https://gPierre56.github.io/conference-ionic/92-es5.c9bd24a34d9a77a3318c.js",
        "https://gPierre56.github.io/conference-ionic/93-es2015.37cb7f9aa5b6f92ff2cc.js",
        "https://gPierre56.github.io/conference-ionic/93-es5.77e82bdb0b4b4b9d9009.js",
        "https://gPierre56.github.io/conference-ionic/94-es2015.155ad25cf131ff39f90e.js",
        "https://gPierre56.github.io/conference-ionic/94-es5.981455b8f210722739b7.js",
        "https://gPierre56.github.io/conference-ionic/95-es2015.12b5f5405715cce87a6a.js",
        "https://gPierre56.github.io/conference-ionic/95-es5.c7d055ffb916d68759c4.js",
        "https://gPierre56.github.io/conference-ionic/96-es2015.3e21d7ee63c20e6c858b.js",
        "https://gPierre56.github.io/conference-ionic/96-es5.9de73efcbafc7f89f447.js",
        "https://gPierre56.github.io/conference-ionic/97-es2015.91b754d70e7424bfc3b1.js",
        "https://gPierre56.github.io/conference-ionic/97-es5.ec070f879aec34a505d4.js",
        "https://gPierre56.github.io/conference-ionic/98-es2015.03af87ccf98fb4aab511.js",
        "https://gPierre56.github.io/conference-ionic/98-es5.7b0d696b2a0981967aa2.js",
        "https://gPierre56.github.io/conference-ionic/99-es2015.e18f295c89a9dc1db917.js",
        "https://gPierre56.github.io/conference-ionic/99-es5.8c6a8a0eebf237b3df20.js",
        "https://gPierre56.github.io/conference-ionic/common-es2015.2b313819100841086229.js",
        "https://gPierre56.github.io/conference-ionic/common-es5.0559d3433f34aed3329d.js",
        "https://gPierre56.github.io/conference-ionic/index.html",
        "https://gPierre56.github.io/conference-ionic/main-es2015.48b28b32d9fe13e1fa02.js",
        "https://gPierre56.github.io/conference-ionic/main-es5.d7d728e77771e8c845f4.js",
        "https://gPierre56.github.io/conference-ionic/polyfills-es2015.0ea0722aab35de3e5eaf.js",
        "https://gPierre56.github.io/conference-ionic/polyfills-es5.27eaa32a15185025327d.js",
        "https://gPierre56.github.io/conference-ionic/runtime-es2015.b77ce1a0bdb6d84b30e5.js",
        "https://gPierre56.github.io/conference-ionic/runtime-es5.de4fd35594a6e032b06b.js",
        "https://gPierre56.github.io/conference-ionic/styles.eb43f98b1cc9e2f11649.css"
      ],
      "patterns": []
    },
    {
      "name": "assets",
      "installMode": "lazy",
      "updateMode": "prefetch",
      "urls": [
        "https://gPierre56.github.io/conference-ionic/assets/icon/favicon.png",
        "https://gPierre56.github.io/conference-ionic/assets/icons/icon-128x128.png",
        "https://gPierre56.github.io/conference-ionic/assets/icons/icon-144x144.png",
        "https://gPierre56.github.io/conference-ionic/assets/icons/icon-152x152.png",
        "https://gPierre56.github.io/conference-ionic/assets/icons/icon-192x192.png",
        "https://gPierre56.github.io/conference-ionic/assets/icons/icon-384x384.png",
        "https://gPierre56.github.io/conference-ionic/assets/icons/icon-512x512.png",
        "https://gPierre56.github.io/conference-ionic/assets/icons/icon-72x72.png",
        "https://gPierre56.github.io/conference-ionic/assets/icons/icon-96x96.png",
        "https://gPierre56.github.io/conference-ionic/assets/logo-devfest-wow.png",
        "https://gPierre56.github.io/conference-ionic/assets/shapes.svg"
      ],
      "patterns": []
    }
  ],
  "dataGroups": [],
  "hashTable": {
    "https://gPierre56.github.io/conference-ionic/1-es2015.506ff25b20e865f460e8.js": "57d109558866e581ed9d591c1242caf25ae89de8",
    "https://gPierre56.github.io/conference-ionic/1-es5.6930c827ef6729028c1a.js": "000a549c7495de8e622e4422d3e3a4dc7af080f4",
    "https://gPierre56.github.io/conference-ionic/10-es2015.455ef8359f6dc028c348.js": "2115a3a1af3a26d336a4e5b6e3996d3db305aeca",
    "https://gPierre56.github.io/conference-ionic/10-es5.3392a83fc6dbe5a1cb6c.js": "83c7fc7a491e64803b78c29a019cf127874539f2",
    "https://gPierre56.github.io/conference-ionic/100-es2015.aaf51250e6baa3942580.js": "4cd26ee218d877f2a4c110e18fcaf8d61dc412f3",
    "https://gPierre56.github.io/conference-ionic/100-es5.1b2321d18c397cddd5ae.js": "b491770092c890be1ab98f5a62ce919c7f7a2d29",
    "https://gPierre56.github.io/conference-ionic/101-es2015.33f5aaeada3454e9d41c.js": "4242360dec87b681a04a594ebaffe987e2e8765e",
    "https://gPierre56.github.io/conference-ionic/101-es5.5497f59ee3ed1801ee9c.js": "29db831435a229ddc95128470258cdcc390cfe8a",
    "https://gPierre56.github.io/conference-ionic/102-es2015.cbab1aa44c65cde1cac0.js": "020a5689a470545e44b8f3106017572289253bf9",
    "https://gPierre56.github.io/conference-ionic/102-es5.ab859ea2111b221607a9.js": "776c659c392922f90950778bb3f6f6e84a6da373",
    "https://gPierre56.github.io/conference-ionic/103-es2015.910841bdf151d3e82aa8.js": "383e374024d53f85f1f4017d1aa5a3dc8707e351",
    "https://gPierre56.github.io/conference-ionic/103-es5.85fc077886fb7201e97b.js": "bb62ac0dcb9fb5a0f8ce41f43e5a9de534d77560",
    "https://gPierre56.github.io/conference-ionic/104-es2015.2149f1ba94fb3bb985cb.js": "c4d4b7c9bc4330fbeff5bed710ef44158eec4980",
    "https://gPierre56.github.io/conference-ionic/104-es5.0f8430d63d716829761b.js": "3f5a634f710f3ce8ab6682c3e55a07ec59db27c6",
    "https://gPierre56.github.io/conference-ionic/105-es2015.3aa7b622d24f39954d3c.js": "0b0a5e780a335f6ea8fc0371f6fd685034ff0b47",
    "https://gPierre56.github.io/conference-ionic/105-es5.6dc9170fa5eedff740b6.js": "a54e8fbecfa976c8dfd2a4d7bc537cc25b3b2a9e",
    "https://gPierre56.github.io/conference-ionic/106-es2015.84bedd65d4c90aac0e48.js": "2427062b26f094f4e04afec44d1fb19b0ab17729",
    "https://gPierre56.github.io/conference-ionic/106-es5.8a9e5da74fd7de53ff56.js": "2427062b26f094f4e04afec44d1fb19b0ab17729",
    "https://gPierre56.github.io/conference-ionic/107-es2015.67f6da47f7cb183a9d5e.js": "441af8262a51d6aeb9e067890d1dfb3d079a566d",
    "https://gPierre56.github.io/conference-ionic/107-es5.5b23804aac2b17b0c89e.js": "441af8262a51d6aeb9e067890d1dfb3d079a566d",
    "https://gPierre56.github.io/conference-ionic/108-es2015.3b8a75f77830a8b67a55.js": "b2f50516735395c1b72104694322859ced41de4b",
    "https://gPierre56.github.io/conference-ionic/11-es2015.97e44b7d061609ac3248.js": "07e6e5e1a841b0521b3fb77c62717d1c73c7ea62",
    "https://gPierre56.github.io/conference-ionic/11-es5.f6f476ba7e4e398b0476.js": "5b42196d61b2089847adedc039eb0c586105a3d4",
    "https://gPierre56.github.io/conference-ionic/14-es5.b915df1d3775570a79b5.js": "b1c6f65b5b65e850caf69efa0c26710a6befd1a5",
    "https://gPierre56.github.io/conference-ionic/15-es2015.a48e7a64a16d8d73f0ab.js": "c055df0d06113e5a6be81623be0eef61c328b889",
    "https://gPierre56.github.io/conference-ionic/15-es5.b25ce20251ca6ab5a772.js": "ab0ddc2d07470fbc9aef6d8b0114f721bacbd374",
    "https://gPierre56.github.io/conference-ionic/16-es2015.85e3cae62ec7dd4cbc77.js": "fc993a7f92dd11c2f99eef1e9aac01dd82e4e755",
    "https://gPierre56.github.io/conference-ionic/16-es5.b527e30b716540129a00.js": "4010c912799a0cb9fc2651c86a1e3d98540b27ec",
    "https://gPierre56.github.io/conference-ionic/17-es2015.c0a615fc11a491cf42b7.js": "328759385c67e28a4145c83ca22ca87694be25ad",
    "https://gPierre56.github.io/conference-ionic/17-es5.255eee7b5c1fe0ab299b.js": "d8e2c8c85ed08269b6dbe3b129ffd106f17629ec",
    "https://gPierre56.github.io/conference-ionic/18-es2015.7e0de0af7fc56bbce2ce.js": "210d4438c2de6e6002968e05e1bfb05817ce2a34",
    "https://gPierre56.github.io/conference-ionic/18-es5.d98d198729100506a5df.js": "4de31cda9e123a2a9ebb1804644aea54a0086e5e",
    "https://gPierre56.github.io/conference-ionic/19-es2015.9bc0dfb9ed71d85da520.js": "17616a85fb5bbe88fc30ea28ae48dba337b44945",
    "https://gPierre56.github.io/conference-ionic/19-es5.f760cb2a84b20258791d.js": "685bc02bb546a97f84d8dd49b6f52d9885f1ce40",
    "https://gPierre56.github.io/conference-ionic/2-es5.6f6b2d6e12a843531dd6.js": "5eded6ca470eef8c77de9cada577b26e31779cc2",
    "https://gPierre56.github.io/conference-ionic/20-es2015.dfe600a78fe380c1686b.js": "5fd2ddaac774fb5358e95358ffc6f1041644dd43",
    "https://gPierre56.github.io/conference-ionic/20-es5.8d3f6669648ea4b900c5.js": "e2ba7ff5235b0aa0a51465aeeaf72d995b41186c",
    "https://gPierre56.github.io/conference-ionic/21-es2015.dccd515fe19983dd1bd9.js": "31068539deda50f8938e5bf1af193b646305b12d",
    "https://gPierre56.github.io/conference-ionic/21-es5.1e5284b2a22f6ebff3c7.js": "588d8088e919440a45979554dd26f806fa033e6a",
    "https://gPierre56.github.io/conference-ionic/22-es2015.b0736d043c78a0d66f46.js": "85c00f73305cd5ec50610fd9db4656d76b936e26",
    "https://gPierre56.github.io/conference-ionic/22-es5.ebf07d37eb5c607c2d4f.js": "55e5dca63ee3ca7117720eef3bedf559aa38e681",
    "https://gPierre56.github.io/conference-ionic/23-es2015.32e06cbaa8d6e427fdc7.js": "76b47dd8d2a7d135158b0d225b0942381c4c9eff",
    "https://gPierre56.github.io/conference-ionic/23-es5.b3e8e472d9070605a48c.js": "5bd6642fc3c58c4224f745b9396fbe7a86cb0825",
    "https://gPierre56.github.io/conference-ionic/24-es2015.2fc0339b566cc91ddf0d.js": "52f60c596c7c8c8a83472506ccee20aae57cac46",
    "https://gPierre56.github.io/conference-ionic/24-es5.1dc15dbb0f0c8dab69be.js": "1ccc47994f9a7a0b69625b0c37f19eaf6b4b7ca5",
    "https://gPierre56.github.io/conference-ionic/25-es2015.e39eb0d5961ee4214800.js": "6e5b2079c74db6a96041d8aeadd0363b87b40e6e",
    "https://gPierre56.github.io/conference-ionic/25-es5.abec9e00e60a27ea15fa.js": "049061abd66b5594111b656077871828f7526153",
    "https://gPierre56.github.io/conference-ionic/26-es2015.4f5042b04262fc141030.js": "05a15f88f2aa14273b51f62baaa353e701ae535d",
    "https://gPierre56.github.io/conference-ionic/26-es5.12f3ec8290d310c56590.js": "4b6e364ffc2749395970526a1cdc4db389efb20e",
    "https://gPierre56.github.io/conference-ionic/27-es2015.3096d4e5b8f222489a80.js": "3690204ddd75a867cf3204cd85bfa3f9e646086c",
    "https://gPierre56.github.io/conference-ionic/27-es5.2c64b9e233c503f6d9a2.js": "233c4aa020c5234cc73b3e672a35db309fbc25ce",
    "https://gPierre56.github.io/conference-ionic/28-es2015.5641e573373a63d7e104.js": "4c47cc4cd95b96aa4e40bb5ab2f96adf5d6d32a9",
    "https://gPierre56.github.io/conference-ionic/28-es5.b3cd899787837c08a715.js": "0d6ed7e84aa5d4e56ee23236c58fae9b6110d565",
    "https://gPierre56.github.io/conference-ionic/29-es2015.ea3d302ad4c58081baec.js": "579d1bd7b56110551fe16471d1f9b444f2a545e3",
    "https://gPierre56.github.io/conference-ionic/29-es5.e1b8fe1123ed93716db5.js": "51ae7e5aadb9f2e8cdbe0ef6b1f1d7dac2c07c72",
    "https://gPierre56.github.io/conference-ionic/3-es2015.d6ac8d704fa8c21d31e7.js": "dc49b8288dab1a8ba52500efea7cbb0d9e37a3be",
    "https://gPierre56.github.io/conference-ionic/30-es2015.d31d5897b87fceb212b3.js": "be95e29ef9157a8f6767250504c3562819d924e6",
    "https://gPierre56.github.io/conference-ionic/30-es5.561b08026c587a74d39e.js": "ee5e2664c6530cb1ef63f66723e50aa6d893df46",
    "https://gPierre56.github.io/conference-ionic/31-es2015.f15ac1eceb9da0315c5d.js": "c362b1962811941751d9eef6e2ebdf01eb66dc5e",
    "https://gPierre56.github.io/conference-ionic/31-es5.c283b8521f673444cab0.js": "6e02036c1c565aa8be9fb1c2f040f2907ebc47e7",
    "https://gPierre56.github.io/conference-ionic/32-es2015.34b25343c16e47ccec94.js": "014bda5270337902ddc34ee3949cf02344d90c01",
    "https://gPierre56.github.io/conference-ionic/32-es5.eaa40abede764cf1166e.js": "e5f8d1560d05cdf1bdb2966ff4cd1ca09dad5c11",
    "https://gPierre56.github.io/conference-ionic/33-es2015.f95f44e6ac331288aa43.js": "46308b30b598f3ec0ebfcbf735b83e534342ce93",
    "https://gPierre56.github.io/conference-ionic/33-es5.55245bd8a37a3fa95b45.js": "6ddadec669dbb80de119cca975de9adb40a95f21",
    "https://gPierre56.github.io/conference-ionic/34-es2015.645d89d2c43f107274fd.js": "0941b1fb4e147863153ea9bd1c42c911e9a78e87",
    "https://gPierre56.github.io/conference-ionic/34-es5.59dd8835b5003255b3e6.js": "634da32ce25515501313650c42a5a5a0580f5a8a",
    "https://gPierre56.github.io/conference-ionic/35-es2015.260c0991913dde1c4b41.js": "a1618bfb2f9e06ccd03c7ff9fc4950d6de7d027f",
    "https://gPierre56.github.io/conference-ionic/35-es5.69118e65501ab528c274.js": "31e1f120d8732b0c0443f7f6c1251be8e6273537",
    "https://gPierre56.github.io/conference-ionic/36-es2015.3c8798b13b4059f656c9.js": "2d458c5d78d9a5f98300ea71aaf24690226ce0f7",
    "https://gPierre56.github.io/conference-ionic/36-es5.6b82c1657c44f3940ca0.js": "ed70ac56aa8411839222cd55945ae4397729b512",
    "https://gPierre56.github.io/conference-ionic/37-es2015.1392128ef0f8c2bce11d.js": "d4e556553af908f53cd87739740f555a86595f86",
    "https://gPierre56.github.io/conference-ionic/37-es5.3ff11b07b7f9a103c293.js": "d725cf533d95f91f57dd26782e50b2b20317a100",
    "https://gPierre56.github.io/conference-ionic/38-es2015.00d37447fe2e0fe53155.js": "0a4376ad47dd9730c34a56ad2748206eb79cfe49",
    "https://gPierre56.github.io/conference-ionic/38-es5.79997d83d7d8f79ff4ea.js": "45816a71ba005eec1a5f828173328af79be33028",
    "https://gPierre56.github.io/conference-ionic/39-es2015.e7a29d89e6eb40eda240.js": "c06576adae4dd95e33644995ad7dc8bed2776d19",
    "https://gPierre56.github.io/conference-ionic/39-es5.cdc4d4564284188f4402.js": "b33a65742993541647d05e914e5925cab94da8fe",
    "https://gPierre56.github.io/conference-ionic/4-es2015.371c8f0a5554410fe343.js": "8ad0003a8fe1574f9bf0c289e267cc0d0c41b72f",
    "https://gPierre56.github.io/conference-ionic/4-es5.edabf8227e7fef5c841c.js": "90f66579a7273bb29dbe496336da6965baa7a03b",
    "https://gPierre56.github.io/conference-ionic/40-es2015.15e987d96911d8c1cf94.js": "c0e6afa5cd470138ed043e7d0c398b880fa11a05",
    "https://gPierre56.github.io/conference-ionic/40-es5.d668b0f5d1d6ec7d02a4.js": "d8881a67c07410ac8cde6ac4e8d41efc5c13eb98",
    "https://gPierre56.github.io/conference-ionic/41-es2015.772424b3620d34853f41.js": "beb70b3b501f8c0b99d6dac5148f5da560d4bf18",
    "https://gPierre56.github.io/conference-ionic/41-es5.9217e193184c49fe4eda.js": "4316552563e63a76046545a4a9dd92219bcf89a1",
    "https://gPierre56.github.io/conference-ionic/42-es2015.e137dbbb78837b3e05a1.js": "add8f0754d490a8c000592fcf57cc6309e95e517",
    "https://gPierre56.github.io/conference-ionic/42-es5.6299ce27a36e2f45b1db.js": "5c6da83bfd257e13f44bf2536c0bfa4e8a2e79a0",
    "https://gPierre56.github.io/conference-ionic/43-es2015.6298e4dab0981848673e.js": "22885722b03236b11ad72ced7813f73c08e472ff",
    "https://gPierre56.github.io/conference-ionic/43-es5.c6841a141d717509bed0.js": "594ac92ec0b0c2842946c6fe2e1f3dce90df7ca7",
    "https://gPierre56.github.io/conference-ionic/44-es2015.c7dbd2b671620f98113a.js": "8724859e9f05c9cd8445dec9b386f17e9b04b2e1",
    "https://gPierre56.github.io/conference-ionic/44-es5.048dff59bed0fcf8a167.js": "f61b692a8430d7b192866899a26352573ae3b5db",
    "https://gPierre56.github.io/conference-ionic/45-es2015.66ffd27c58acdd84ade6.js": "19d43d4b2c96ef58ab183c0a9fb455012040f456",
    "https://gPierre56.github.io/conference-ionic/45-es5.7ded4915d9d9405a3696.js": "8b20648804f6463f6a401d1146e0631cd5066b9d",
    "https://gPierre56.github.io/conference-ionic/46-es2015.1641f73d2a8a3380366e.js": "4914a01f6554bd3af7a793b97fad7a9cfa116c80",
    "https://gPierre56.github.io/conference-ionic/46-es5.22724aaa4ee2c0e513bb.js": "9cd0367d169437f4103f0dae7aa1d447a58d805a",
    "https://gPierre56.github.io/conference-ionic/47-es2015.db5ef8d3e342b9b27ff0.js": "0f0a5426798ad9d9ab8d3ee22e4475b7ee1dc253",
    "https://gPierre56.github.io/conference-ionic/47-es5.917398f6c026b709a7d9.js": "738d7e74e9e5da3a20e0af0834bcfb941e108b93",
    "https://gPierre56.github.io/conference-ionic/48-es2015.950a861e96b11425e199.js": "ae185a48b7d3da1d3deda675705b9f59a275bc0d",
    "https://gPierre56.github.io/conference-ionic/48-es5.7bbd43864e352a9a34cc.js": "56478128bdf62bd4883deb8bbd253cc48776386b",
    "https://gPierre56.github.io/conference-ionic/49-es2015.14f7060d83207c319a27.js": "1f118c550ec81a7a1eb5ce0fcd0bab4fd387b126",
    "https://gPierre56.github.io/conference-ionic/49-es5.ee3c28c41931140f7f98.js": "3ecb07b86fa9c00066e08bd4aee830acd7bd6f43",
    "https://gPierre56.github.io/conference-ionic/5-es2015.86cf410eedc475bc352d.js": "387ed307498f0089c3ad6bf47282af3faa8e62b8",
    "https://gPierre56.github.io/conference-ionic/5-es5.6102aae1e25434463526.js": "eeaca39063b3564a04ff4cb136da6c32a5cdebb4",
    "https://gPierre56.github.io/conference-ionic/50-es2015.cfa9c782f46594af2afc.js": "cc91cda0a547a8505e8dcb336d7bb83ea4fae7ad",
    "https://gPierre56.github.io/conference-ionic/50-es5.ef26b16a0d45f52b5b91.js": "2961725367f6ec2e1fb5088907701a81359cfce7",
    "https://gPierre56.github.io/conference-ionic/51-es2015.7c4054d82b9d309962cc.js": "0c68b2c14b457b70777bd9fafd19015f9278c169",
    "https://gPierre56.github.io/conference-ionic/51-es5.b2b3f52ff58de9410ea1.js": "7994350837f354f464989c47a1a14254bac96790",
    "https://gPierre56.github.io/conference-ionic/52-es2015.68a8aae41cc7c817b672.js": "6ffbc82c0391c0f2f34beb65f8c6d429a34ecf72",
    "https://gPierre56.github.io/conference-ionic/52-es5.417abfbe7aaa42ede37b.js": "1d90ae45f7ed04ad0361d980e662a30c5e6d2198",
    "https://gPierre56.github.io/conference-ionic/53-es2015.a6d5de20e7a55b381656.js": "6c3dc89fbc9b63d4b51de75703e37a44cafbade7",
    "https://gPierre56.github.io/conference-ionic/53-es5.3e73abe68375da46dcb6.js": "d9b670d6b3bf74d06089e04cb7c1a609571cdd51",
    "https://gPierre56.github.io/conference-ionic/54-es2015.93655bb7d36902e6beae.js": "ca1cce4a2e2e7b6de68a35fb5745d41e5331dd98",
    "https://gPierre56.github.io/conference-ionic/54-es5.73477fe316a56c004d0e.js": "67fbababfb6eb8bfc88373dbcd8bb88613f54a13",
    "https://gPierre56.github.io/conference-ionic/55-es2015.951877a27feab8a3fb4d.js": "607342692200f5926c8e872ff6558f5b7d9f6dc3",
    "https://gPierre56.github.io/conference-ionic/55-es5.4b166133326eef8ce942.js": "c53423abf073ebc404073bb4f4c60fc92a33915d",
    "https://gPierre56.github.io/conference-ionic/56-es2015.048de950cbd88c193ff9.js": "7a9c5f858bec26a7a9d533cfca2738931bc905e0",
    "https://gPierre56.github.io/conference-ionic/56-es5.4847a7cbaaeb3592a353.js": "e52fa03fe2bb29e583f802a5268ef00fd9191f22",
    "https://gPierre56.github.io/conference-ionic/57-es2015.e11902d0fd03853c7a1d.js": "e76d6e6c6fac486a37bce0f5cf63f497b84d8aac",
    "https://gPierre56.github.io/conference-ionic/57-es5.0bc7f30eb476df0aa0bc.js": "2d2e0c3a358383a541ac4cbb9fa937d8588eca8e",
    "https://gPierre56.github.io/conference-ionic/58-es2015.b406f7bc5ae1436da0b1.js": "36e3eaba3bc88289a8f150ad7a221d0f0c29e5cd",
    "https://gPierre56.github.io/conference-ionic/58-es5.0be5ddc2aa773f33f08c.js": "6a338d555317e7c4b0d567a991115027aca30870",
    "https://gPierre56.github.io/conference-ionic/59-es2015.b51890c42ba9a1e96727.js": "c9b20e92f2d11617c0b5f27612ff2f4b068e6fc7",
    "https://gPierre56.github.io/conference-ionic/59-es5.9cdffe95c18e41fe446d.js": "4b5b90cddd65750837766e5e9748c5922362055c",
    "https://gPierre56.github.io/conference-ionic/6-es2015.4993ef75f626ddf24fe7.js": "04ca920d7801dafc1cd884abb8efefda0470e089",
    "https://gPierre56.github.io/conference-ionic/6-es5.376fc0f1fcc0c5e8bac8.js": "a9576d345c00fce230e22b0cd3c02cfe6c2292cf",
    "https://gPierre56.github.io/conference-ionic/60-es2015.2825494580af64205f7f.js": "9a0f0d77d903ac27744f4c82a863279725f4c726",
    "https://gPierre56.github.io/conference-ionic/60-es5.e256bbfe13c4861b4220.js": "faee0f31c05e0d57e1b5c771e99c1ddbe7a4ae0e",
    "https://gPierre56.github.io/conference-ionic/61-es2015.1604474cf28536fc2b95.js": "58fc5f3adfc2f55155e02c4843ae7475e094716c",
    "https://gPierre56.github.io/conference-ionic/61-es5.bae29f59dab18fb16549.js": "c4b251f409b6223ba1beb84b1308aa48807117a5",
    "https://gPierre56.github.io/conference-ionic/62-es2015.30ec7cb05ab02ea0eddd.js": "f98fcb7d5afad606d126e83c3e4a54c63c96fba8",
    "https://gPierre56.github.io/conference-ionic/62-es5.857fd05cf62531bd7f76.js": "8229c51ce5f80fc2e61d1fdc448ba63da5904a33",
    "https://gPierre56.github.io/conference-ionic/63-es2015.594228baeaf7c619f242.js": "3a89f74dcb299581cab38bda01ca2ad0fbd55323",
    "https://gPierre56.github.io/conference-ionic/63-es5.87fbb8fb55731612ff29.js": "c027f3c0a376e683dcbb9387be75d00eaeac1789",
    "https://gPierre56.github.io/conference-ionic/64-es2015.8ae119398f7f12b8c784.js": "a92ecab29779511bc7e504dcbb74d24da8fb8382",
    "https://gPierre56.github.io/conference-ionic/64-es5.19182598fed99a197593.js": "b72b1e74b39cc3d2dff3e6d78999c6a2d46758c9",
    "https://gPierre56.github.io/conference-ionic/65-es2015.10f7e4a3d15739f4b934.js": "05a13cde8d0146184a27b13004f0b327c9f58026",
    "https://gPierre56.github.io/conference-ionic/65-es5.63b2b7250ebead0b015b.js": "97611b4b5f51496e70b9bd3074a2a6c9623a1514",
    "https://gPierre56.github.io/conference-ionic/66-es2015.c53b72ad48a60cfe9f32.js": "118d5d2f36043ad9673e562fb3c60b25a6f429e6",
    "https://gPierre56.github.io/conference-ionic/66-es5.08b288969ab7d2331904.js": "41644d0dad4dec09c3fc765637da8ea554d96f79",
    "https://gPierre56.github.io/conference-ionic/67-es2015.99fe52f2e79ffdd1dcbd.js": "471f26e3f3a472e794427fe9978b5163de80a51c",
    "https://gPierre56.github.io/conference-ionic/67-es5.bf861e22959300768938.js": "e6b7f8466099389f6b4d063069740a9f19d5725c",
    "https://gPierre56.github.io/conference-ionic/68-es2015.744f7eb16ebc0ed2a97e.js": "24a9f9e6cbe6946d391d25430bf107ee2117af33",
    "https://gPierre56.github.io/conference-ionic/68-es5.31bd41f78c5d45822e6d.js": "dc2e242c0cbaeb3914731fa831bc3d0d7b17bd66",
    "https://gPierre56.github.io/conference-ionic/69-es2015.7578175b187a4f2c0eca.js": "2b6e42f2e4a62c3a724d42f08c35b4796f8b9cf5",
    "https://gPierre56.github.io/conference-ionic/69-es5.c3e199b940322f180e0f.js": "54064f56f88eeecf8ddc9e7a3ab9a94c13bf084c",
    "https://gPierre56.github.io/conference-ionic/7-es2015.b444c9948e95b49214bf.js": "07973e3acd6057c2205d56aa2e991dab13a6058d",
    "https://gPierre56.github.io/conference-ionic/7-es5.0e9f9439eaf8c9ddf366.js": "92d12ae3f4c8ce209cede86dc324891af088aec1",
    "https://gPierre56.github.io/conference-ionic/70-es2015.690c1df7fb385e6cd1bd.js": "88ce59fbc6bc82077b9e4c7d1e8c4431568f2a87",
    "https://gPierre56.github.io/conference-ionic/70-es5.99bccd79a0cdc27dc567.js": "45b0d13d70c0aef5a02a45d6a6c615399df3eaa2",
    "https://gPierre56.github.io/conference-ionic/71-es2015.4741b251e9e13645fb02.js": "0d6ea066714e4d234a6e0d3930ed3b0cdfa83cd4",
    "https://gPierre56.github.io/conference-ionic/71-es5.9fbad1a0115097f7d905.js": "c20e9422893469cb665169d24398b9373dd5bee0",
    "https://gPierre56.github.io/conference-ionic/72-es2015.d91b2777af3836f84acc.js": "b00d02eae91d7ec8903ceec69718faee6d200407",
    "https://gPierre56.github.io/conference-ionic/72-es5.572c39ea88b2c131a981.js": "04412f7285959b935fa6ebad40526c2586386d97",
    "https://gPierre56.github.io/conference-ionic/73-es2015.f3e6da05c211ee94bcd2.js": "e2a68667265295d9f3f938b36cb865f9148f6062",
    "https://gPierre56.github.io/conference-ionic/73-es5.50e3a69dc9d5c0a8c3e1.js": "e1761177c3d0c8e31c0de2657781945fa71417ae",
    "https://gPierre56.github.io/conference-ionic/74-es2015.d607ec0ea03027f94da9.js": "3dfde654d8cf6e95ca510b19b974e1373b77d313",
    "https://gPierre56.github.io/conference-ionic/74-es5.7f646a21628a384553f7.js": "2292d18ba7af2d784635b723fb94be7c58ad8f1c",
    "https://gPierre56.github.io/conference-ionic/75-es2015.f3cd6953b483750c0701.js": "f9c15aebb7ee36a22022348ee213e75e6bbc7a31",
    "https://gPierre56.github.io/conference-ionic/75-es5.26ff06fedb95681e5ab3.js": "ac719acac437488e5d4a89c07a68dbd085ae4d76",
    "https://gPierre56.github.io/conference-ionic/76-es2015.dc1bb06bcf0ab80f26fe.js": "d4c05fbbffb14c839db75e9ec2fe615e29e1e879",
    "https://gPierre56.github.io/conference-ionic/76-es5.a99eb5fce07ac1d9a855.js": "93e76e745a581a570df528765c6b5dd578fe1cd6",
    "https://gPierre56.github.io/conference-ionic/77-es2015.9e99489ca921e8d183b4.js": "5b8cd413eba3e7e173b956884ed163616541843c",
    "https://gPierre56.github.io/conference-ionic/77-es5.8210b01549fac032d908.js": "40ded7b1d5f7993b7b68fd03534a949f38275a9c",
    "https://gPierre56.github.io/conference-ionic/78-es2015.506df84b45c56d27814e.js": "a8113831e6d8bfadd2784760bb2d8a03cf9676b7",
    "https://gPierre56.github.io/conference-ionic/78-es5.3eea6b4fb9863a46da85.js": "2b94368df30f7c55cd88bbfd11c6ea5082f04d99",
    "https://gPierre56.github.io/conference-ionic/79-es2015.5d7ab4a7066d74b95014.js": "6267699ad8aafa586c7059e28be3673f5d81afc2",
    "https://gPierre56.github.io/conference-ionic/79-es5.d634204efcea24eeb90c.js": "cc4db5d7db1fb880f88f9e786b6cbebc100cb41a",
    "https://gPierre56.github.io/conference-ionic/8-es2015.c1fa4b5905a5429a6aa8.js": "4b29a0a20544e40abc9f5ca3ccf5c5e6ebfb8ab8",
    "https://gPierre56.github.io/conference-ionic/8-es5.c443222dbdfb1d668d2d.js": "77a43a2485d61b183c278b528b3e8c47f89424ff",
    "https://gPierre56.github.io/conference-ionic/80-es2015.fbcfa2255d588aa14293.js": "e1cfc92d2fbf290ca2b961cc63d0bbc7cae290a0",
    "https://gPierre56.github.io/conference-ionic/80-es5.03dcc11f84995640d6bf.js": "174ec7a7e5e4c54c73c4cf09287bf88b279098d8",
    "https://gPierre56.github.io/conference-ionic/81-es2015.dda141d7a3dd6222409c.js": "e1511eb435bc4781640881b6d6165651cdb9ab6c",
    "https://gPierre56.github.io/conference-ionic/81-es5.d0c189d84c760b74a80d.js": "863c22e05735b001fe8bebb69041faf01581e4c3",
    "https://gPierre56.github.io/conference-ionic/82-es2015.60b9e137c00308184784.js": "cb991d71a547ebc1dac9475347be19d3841d2ac7",
    "https://gPierre56.github.io/conference-ionic/82-es5.20317392ff5496a266fc.js": "f29932fac33834e34eb8ffb06fdca360a439cc6b",
    "https://gPierre56.github.io/conference-ionic/83-es2015.8a2a0332334790c287d7.js": "c8bff83da78287dd611121644fa4e7228bbd7618",
    "https://gPierre56.github.io/conference-ionic/83-es5.dcca598ca67a95acd6d7.js": "11524de761ee555dac6cf3814157dd30548f952f",
    "https://gPierre56.github.io/conference-ionic/84-es2015.442f9e5c3e8f736e718b.js": "8efc153aed0939b182f6c84646e31e678fa22537",
    "https://gPierre56.github.io/conference-ionic/84-es5.619b30d5f504326e23c4.js": "3c05ea9c60aee37fb87c1288803068690e88e9b0",
    "https://gPierre56.github.io/conference-ionic/85-es2015.779a16fab2997558968b.js": "a92d94f5c409513676c4847aad958af581d81f25",
    "https://gPierre56.github.io/conference-ionic/85-es5.2641a7f2f9b23e2b9daf.js": "98e110df626d7a7e0f6d59c0eec4736ccd21c575",
    "https://gPierre56.github.io/conference-ionic/86-es2015.afec048412c0677beeb4.js": "cdbe03fc3453a302e6b77c31c47d71085870bf2b",
    "https://gPierre56.github.io/conference-ionic/86-es5.8963782ad70b13ea76a9.js": "51c061f07244ba5e2f8954f127ed523282663f4d",
    "https://gPierre56.github.io/conference-ionic/87-es2015.1604898ef93b623d15d8.js": "78a0605bc855702c9dc43bc3eca56f466b2f2c4b",
    "https://gPierre56.github.io/conference-ionic/87-es5.2f09513c8a15168324e8.js": "bca1105c59052d1f73023c613fdcffe5a517f938",
    "https://gPierre56.github.io/conference-ionic/88-es2015.b809d6b8e8cf95f110d9.js": "86f455064dab4029e9cec25428d3cf870a3df33f",
    "https://gPierre56.github.io/conference-ionic/88-es5.2d92dfd4298205600aa7.js": "18c13c6be9e1c22fef85d9d6e97784f56e46cc16",
    "https://gPierre56.github.io/conference-ionic/89-es2015.956be521b707756d3fd1.js": "aad0715a24edaff95cb4f847bacafb556fbdc40c",
    "https://gPierre56.github.io/conference-ionic/89-es5.197ccab10bb4d345e43d.js": "8793cf98deb4797fb8a0775f3b9de9139cea2a23",
    "https://gPierre56.github.io/conference-ionic/9-es2015.291f8c220aba2f0e0034.js": "b61ce6fecf32bc78c072c6fb2921f76a02348eb8",
    "https://gPierre56.github.io/conference-ionic/9-es5.937a5dc11fc15fb92a3c.js": "d1f71b5b1e217818f9b71b873654a0218f520b59",
    "https://gPierre56.github.io/conference-ionic/90-es2015.c477740d144aea238433.js": "dd1e065c72cbc9ec3db4b72e014f477ef484d3ee",
    "https://gPierre56.github.io/conference-ionic/90-es5.6bc191813da03929ac5e.js": "924ff5d5f5a5dd619b49ba0267a7471af8a9698d",
    "https://gPierre56.github.io/conference-ionic/91-es2015.7b30a8097f1f36565c18.js": "b4eb4dd5942a1b84a319caa4257dbcf2f45d0743",
    "https://gPierre56.github.io/conference-ionic/91-es5.b2c4cb933948b7c1dfc9.js": "7a5deff7d571dfc0dd9210b5f2ab210684acd274",
    "https://gPierre56.github.io/conference-ionic/92-es2015.6e3def503fa6b508d7bd.js": "5c9dccc562fffbc44bc5d12cc77e067ee14a4269",
    "https://gPierre56.github.io/conference-ionic/92-es5.c9bd24a34d9a77a3318c.js": "2e8ae6e3ac712146adf68ef093e1d2606aa260dc",
    "https://gPierre56.github.io/conference-ionic/93-es2015.37cb7f9aa5b6f92ff2cc.js": "073859803ebb93e559fea99c39498390f4bcdf1a",
    "https://gPierre56.github.io/conference-ionic/93-es5.77e82bdb0b4b4b9d9009.js": "5ffb0d76dbf16ffde3c50316cfcd65a89a534c00",
    "https://gPierre56.github.io/conference-ionic/94-es2015.155ad25cf131ff39f90e.js": "c0e2ec9e408c2238f950727ca56d76f452bc1f70",
    "https://gPierre56.github.io/conference-ionic/94-es5.981455b8f210722739b7.js": "cdbeb1af2fe57f4bda9e3b9ef174e11f8b0266ef",
    "https://gPierre56.github.io/conference-ionic/95-es2015.12b5f5405715cce87a6a.js": "e2868669da2f51faacf3adb49f568975fa92db74",
    "https://gPierre56.github.io/conference-ionic/95-es5.c7d055ffb916d68759c4.js": "12313417475a0c7f94a34d4f10187dfb418153cc",
    "https://gPierre56.github.io/conference-ionic/96-es2015.3e21d7ee63c20e6c858b.js": "49f882847525bc639bd22c65054868fa1dc8c3f9",
    "https://gPierre56.github.io/conference-ionic/96-es5.9de73efcbafc7f89f447.js": "e52975df654455558011625ffa913d358d26e61e",
    "https://gPierre56.github.io/conference-ionic/97-es2015.91b754d70e7424bfc3b1.js": "0b6f9b71c05ff89352b922241bfc668e66c9522b",
    "https://gPierre56.github.io/conference-ionic/97-es5.ec070f879aec34a505d4.js": "13ff059a38007ddc5375d60c5827db04576d975a",
    "https://gPierre56.github.io/conference-ionic/98-es2015.03af87ccf98fb4aab511.js": "3270aed3a9608bd55b8cbea51f2e7accd6f042ed",
    "https://gPierre56.github.io/conference-ionic/98-es5.7b0d696b2a0981967aa2.js": "402549a87157e4d44c04be85c129112693a777f0",
    "https://gPierre56.github.io/conference-ionic/99-es2015.e18f295c89a9dc1db917.js": "69dad242a80f59ecac4c72d12450e25f31c56e2a",
    "https://gPierre56.github.io/conference-ionic/99-es5.8c6a8a0eebf237b3df20.js": "39f846839e7400688f75c481b59a8c64c0b18cf2",
    "https://gPierre56.github.io/conference-ionic/assets/icon/favicon.png": "7798b8e0eb61d7375c245af78bbf5c916932bf13",
    "https://gPierre56.github.io/conference-ionic/assets/icons/icon-128x128.png": "dae3b6ed49bdaf4327b92531d4b5b4a5d30c7532",
    "https://gPierre56.github.io/conference-ionic/assets/icons/icon-144x144.png": "b0bd89982e08f9bd2b642928f5391915b74799a7",
    "https://gPierre56.github.io/conference-ionic/assets/icons/icon-152x152.png": "7479a9477815dfd9668d60f8b3b2fba709b91310",
    "https://gPierre56.github.io/conference-ionic/assets/icons/icon-192x192.png": "1abd80d431a237a853ce38147d8c63752f10933b",
    "https://gPierre56.github.io/conference-ionic/assets/icons/icon-384x384.png": "329749cd6393768d3131ed6304c136b1ca05f2fd",
    "https://gPierre56.github.io/conference-ionic/assets/icons/icon-512x512.png": "559d9c4318b45a1f2b10596bbb4c960fe521dbcc",
    "https://gPierre56.github.io/conference-ionic/assets/icons/icon-72x72.png": "c457e56089a36952cd67156f9996bc4ce54a5ed9",
    "https://gPierre56.github.io/conference-ionic/assets/icons/icon-96x96.png": "3914125a4b445bf111c5627875fc190f560daa41",
    "https://gPierre56.github.io/conference-ionic/assets/logo-devfest-wow.png": "ee9fb13d2ca96c10d3ef94b26253b68222f3ec77",
    "https://gPierre56.github.io/conference-ionic/assets/shapes.svg": "5413e95adabcb2cb639970051f55e0ddb64ace53",
    "https://gPierre56.github.io/conference-ionic/common-es2015.2b313819100841086229.js": "ba35eb2bdd26b0051626606344cc1bd9a1fcb917",
    "https://gPierre56.github.io/conference-ionic/common-es5.0559d3433f34aed3329d.js": "9657db6d4e6d0bf42a675e1581504a80742c2ecf",
    "https://gPierre56.github.io/conference-ionic/index.html": "f264a65c79149976d2e990a7c82ff91a4a15bab7",
    "https://gPierre56.github.io/conference-ionic/main-es2015.48b28b32d9fe13e1fa02.js": "2b445f7d8db60beb5c3c5a772707e9f742bf5ff6",
    "https://gPierre56.github.io/conference-ionic/main-es5.d7d728e77771e8c845f4.js": "18fe381110d4207d4095fde725a7d2c5f8370308",
    "https://gPierre56.github.io/conference-ionic/polyfills-es2015.0ea0722aab35de3e5eaf.js": "1d6042b487a61f39c92b5bea4644fe26cc3f8fd8",
    "https://gPierre56.github.io/conference-ionic/polyfills-es5.27eaa32a15185025327d.js": "cfa5e327db4dc300ac2951218fcfecb2ae4b4b73",
    "https://gPierre56.github.io/conference-ionic/runtime-es2015.b77ce1a0bdb6d84b30e5.js": "5b7ed0895a75c863c0b871e4b24c5cb256e88093",
    "https://gPierre56.github.io/conference-ionic/runtime-es5.de4fd35594a6e032b06b.js": "468a6a29e86cb2bdaef4d3745308b942a736889b",
    "https://gPierre56.github.io/conference-ionic/styles.eb43f98b1cc9e2f11649.css": "9b4b32e8d0c6e3c51bad8337849110232996be69"
  },
  "navigationUrls": [
    {
      "positive": true,
      "regex": "^\\/.*$"
    },
    {
      "positive": false,
      "regex": "^\\/(?:.+\\/)?[^/]*\\.[^/]*$"
    },
    {
      "positive": false,
      "regex": "^\\/(?:.+\\/)?[^/]*__[^/]*$"
    },
    {
      "positive": false,
      "regex": "^\\/(?:.+\\/)?[^/]*__[^/]*\\/.*$"
    }
  ]
}